{
    "address1": "Marina Bay Financial Centre",
    "address2": "Tower 3, DBS Asia Central 12 Marina Boulevard",
    "city": "Singapore",
    "zip": "018982",
    "country": "Singapore",
    "phone": "65 6878 8888",
    "fax": "65 6445 1267",
    "website": "https://www.dbs.com",
    "industry": "Banks - Regional",
    "industryKey": "banks-regional",
    "industryDisp": "Banks - Regional",
    "sector": "Financial Services",
    "sectorKey": "financial-services",
    "sectorDisp": "Financial Services",
    "longBusinessSummary": "DBS Group Holdings Ltd provides commercial banking and financial services in Singapore, Hong Kong, rest of Greater China, South and Southeast Asia, and internationally. The company's Consumer Banking/Wealth Management segment offers banking and related financial services, including current and savings accounts, fixed deposits, loans and home finance, cards, payments, investment, and insurance products for individual customers. Its Institutional Banking segment provides financial services and products for bank and non-bank financial institutions, government-linked companies, large corporates, and small and medium sized businesses. Its products and services comprise short-term working capital financing and specialized lending; cash management, trade finance, and securities and fiduciary services; treasury and markets products; and corporate finance and advisory banking, as well as capital markets solutions. The company's Treasury Markets segment is involved in the structuring, market-making, and trading in a range of treasury products. DBS Group Holdings Ltd was founded in 1968 and is headquartered in Singapore.",
    "fullTimeEmployees": 40000,
    "companyOfficers": [
        {
            "maxAge": 1,
            "name": "Mr. Piyush  Gupta",
            "age": 63,
            "title": "CEO & Executive Director",
            "yearBorn": 1960,
            "fiscalYear": 2023,
            "totalPay": 5681992,
            "exercisedValue": 0,
            "unexercisedValue": 0
        },
        {
            "maxAge": 1,
            "name": "Ms. Sok Hui  Lim",
            "age": 62,
            "title": "Chief Financial Officer",
            "yearBorn": 1961,
            "fiscalYear": 2023,
            "exercisedValue": 0,
            "unexercisedValue": 0
        },
        {
            "maxAge": 1,
            "name": "Mr. Hwee Kim  Ng",
            "age": 57,
            "title": "MD, Chief Information Officer and Head of Group Operations",
            "yearBorn": 1966,
            "fiscalYear": 2023,
            "exercisedValue": 0,
            "unexercisedValue": 0
        },
        {
            "maxAge": 1,
            "name": "Mr. Michael  Sia",
            "title": "Head of Investor Relations",
            "fiscalYear": 2023,
            "exercisedValue": 0,
            "unexercisedValue": 0
        },
        {
            "maxAge": 1,
            "name": "Mr. Chee Kin  Lam",
            "title": "MD and Head of Legal & Compliance",
            "fiscalYear": 2023,
            "exercisedValue": 0,
            "unexercisedValue": 0
        },
        {
            "maxAge": 1,
            "name": "Ms. Karen  Ngui",
            "title": "MD & Head of Group Strategic Marketing and Communications",
            "fiscalYear": 2023,
            "exercisedValue": 0,
            "unexercisedValue": 0
        },
        {
            "maxAge": 1,
            "name": "Ms. Yan Hong  Lee",
            "title": "MD & Head of Human Resources",
            "fiscalYear": 2023,
            "exercisedValue": 0,
            "unexercisedValue": 0
        },
        {
            "maxAge": 1,
            "name": "Ms. Su Shan  Tan",
            "age": 55,
            "title": "Group Head of Institutional Banking (IBG)",
            "yearBorn": 1968,
            "fiscalYear": 2023,
            "exercisedValue": 0,
            "unexercisedValue": 0
        },
        {
            "maxAge": 1,
            "name": "Ms. Eng-Kwok  Seat Moey",
            "title": "MD & Group Head of Capital Markets",
            "fiscalYear": 2023,
            "exercisedValue": 0,
            "unexercisedValue": 0
        },
        {
            "maxAge": 1,
            "name": "Mr. Soon Chong  Lim",
            "title": "Group Head of Global Transactions Services & Group Head of Digital for Institutional Banking",
            "fiscalYear": 2023,
            "exercisedValue": 0,
            "unexercisedValue": 0
        }
    ],
    "auditRisk": 1,
    "boardRisk": 1,
    "compensationRisk": 9,
    "shareHolderRightsRisk": 9,
    "overallRisk": 5,
    "governanceEpochDate": 1709251200,
    "compensationAsOfEpochDate": 1703980800,
    "maxAge": 86400,
    "priceHint": 2,
    "previousClose": 33.78,
    "open": 33.88,
    "dayLow": 33.7,
    "dayHigh": 33.95,
    "regularMarketPreviousClose": 33.78,
    "regularMarketOpen": 33.88,
    "regularMarketDayLow": 33.7,
    "regularMarketDayHigh": 33.95,
    "dividendRate": 2.16,
    "dividendYield": 0.064,
    "exDividendDate": 1712275200,
    "payoutRatio": 0.4651,
    "fiveYearAvgDividendYield": 4.72,
    "beta": 0.827,
    "trailingPE": 8.766234,
    "forwardPE": 8.952254,
    "volume": 3486000,
    "regularMarketVolume": 3486000,
    "averageVolume": 4023757,
    "averageVolume10days": 3696265,
    "averageDailyVolume10Day": 3696265,
    "bid": 33.74,
    "ask": 33.75,
    "marketCap": 87257251840,
    "fiftyTwoWeekLow": 30.3,
    "fiftyTwoWeekHigh": 34.55,
    "priceToSalesTrailing12Months": 4.4582696,
    "fiftyDayAverage": 32.7976,
    "twoHundredDayAverage": 32.6657,
    "trailingAnnualDividendRate": 1.92,
    "trailingAnnualDividendYield": 0.056838367,
    "currency": "SGD",
    "enterpriseValue": 145680039936,
    "profitMargins": 0.5141,
    "floatShares": 1825336263,
    "sharesOutstanding": 2585400064,
    "heldPercentInsiders": 0.00975,
    "heldPercentInstitutions": 0.5516,
    "impliedSharesOutstanding": 2585400064,
    "bookValue": 23.151,
    "priceToBook": 1.4578204,
    "lastFiscalYearEnd": 1703980800,
    "nextFiscalYearEnd": 1735603200,
    "mostRecentQuarter": 1703980800,
    "earningsQuarterlyGrowth": -0.073,
    "netIncomeToCommon": 9978000384,
    "trailingEps": 3.85,
    "forwardEps": 3.77,
    "pegRatio": -30.03,
    "lastSplitFactor": "11:10",
    "lastSplitDate": 1713744000,
    "enterpriseToRevenue": 7.443,
    "52WeekChange": 0.032110095,
    "SandP52WeekChange": 0.3288405,
    "lastDividendValue": 0.54,
    "lastDividendDate": 1712275200,
    "exchange": "SES",
    "quoteType": "EQUITY",
    "symbol": "D05.SI",
    "underlyingSymbol": "D05.SI",
    "shortName": "DBS",
    "longName": "DBS Group Holdings Ltd",
    "firstTradeDateEpochUtc": 946861200,
    "timeZoneFullName": "Asia/Singapore",
    "timeZoneShortName": "SGT",
    "uuid": "cb53a270-a97b-3370-933b-1cd7d407b07e",
    "messageBoardId": "finmb_874047",
    "gmtOffSetMilliseconds": 28800000,
    "currentPrice": 33.75,
    "targetHighPrice": 43.14,
    "targetLowPrice": 29.8,
    "targetMeanPrice": 36.55,
    "targetMedianPrice": 37.15,
    "recommendationMean": 2.4,
    "recommendationKey": "buy",
    "numberOfAnalystOpinions": 16,
    "totalCash": 62575001600,
    "totalCashPerShare": 24.262,
    "totalDebt": 121027002368,
    "totalRevenue": 19572000768,
    "revenuePerShare": 7.591,
    "returnOnAssets": 0.0135699995,
    "returnOnEquity": 0.16867,
    "operatingCashflow": 5171999744,
    "earningsGrowth": -0.078,
    "revenueGrowth": 0.087,
    "operatingMargins": 0.4966,
    "financialCurrency": "SGD",
    "trailingPegRatio": 1.5453
}
